dudb/__init__.py
discord_du-1.0.0.dist-info/LICENSE
discord_du-1.0.0.dist-info/METADATA
discord_du-1.0.0.dist-info/WHEEL
discord_du-1.0.0.dist-info/top_level.txt
discord_du-1.0.0.dist-info/RECORD
