Metadata-Version: 2.1
Name: discord-du
Version: 1.0.0
Summary: A API wrapper for Dangerous Users Data Base
Home-page: https://github.com/Stylix58/du.py
Author: Stylix58
Author-email: lateman-jpeg@outlook.fr
License: UNKNOWN
Project-URL: Bug Tracker, https://github.com/Stylix58/du.py/issues
Platform: UNKNOWN
Classifier: Programming Language :: Python :: 3
Classifier: License :: OSI Approved :: MIT License
Classifier: Operating System :: OS Independent
Requires-Python: >=3.6
License-File: LICENSE
